[
  { "id": "eed73c99-1749-474e-86e2-1390bacfa18e", "score": 72, "forYou": true, "reason": "gentle breathwork reset, right up your alley" },
  { "id": "c74d87f7-8c32-46cb-98f9-54a2f2ac6ec2", "score": 74, "forYou": true, "reason": "playful couple's touch workshop, bring your partner" },
  { "id": "20cbbb59-b7d1-4d0b-b3dc-f95248068847", "score": 66, "forYou": true, "reason": "nerdy relationship tools you'd both enjoy" },
  { "id": "263e4b86-e7ff-4021-904d-2c723889d2a2", "score": 34, "forYou": false, "reason": "vague soup-making, low-effort listing" },
  { "id": "9dba7713-d67c-49fd-8edc-2128e42b156d", "score": 68, "forYou": true, "reason": "silly sauna plus cold plunge, restorative fun" },
  { "id": "009401c3-2188-41d9-989f-405a1c999ed1", "score": 70, "forYou": true, "reason": "chaotic lip-sync contest, genuinely fun happening" },
  { "id": "7dfacc84-7e6e-4fc7-8e81-8e2d80c071fc", "score": 42, "forYou": false, "reason": "niche knot-tying card game, mild curiosity" },
  { "id": "2754c2ab-8392-4a7e-81e7-473679675e3c", "score": 48, "forYou": false, "reason": "public-speaking presence exercise, so-so appeal" },
  { "id": "2099e3ad-bf6f-45cc-997e-256ebe8ade1d", "score": 60, "forYou": false, "reason": "fun beatboxing basics, hands-on music skill" },
  { "id": "43068205-5e1d-45d7-87aa-f152963237a2", "score": 71, "forYou": true, "reason": "spicy Polaroid shoot for you two" },
  { "id": "ba981119-f7cf-4d54-8672-32920793f980", "score": 70, "forYou": true, "reason": "leg massage skill-share, bring your partner" },
  { "id": "7368bbdf-63e5-472a-8664-49c9c868a0aa", "score": 74, "forYou": true, "reason": "chill tea, groovy tunes, gentle connection" },
  { "id": "76a8284e-d8c3-4a3e-b144-5a9550e472bb", "score": 55, "forYou": false, "reason": "quirky chakra yoga, gimmicky but fine" },
  { "id": "12fa774f-ddb4-42b7-939b-0fc2e5cf8df1", "score": 72, "forYou": true, "reason": "sensual ice play, trust and connection" },
  { "id": "9b5e4b53-f3af-4cc7-92ef-f00cb29d28b3", "score": 55, "forYou": false, "reason": "silly water fight, kid-friendly afternoon fun" },
  { "id": "f2ab88f5-9d99-4533-a9b3-219e32082a5b", "score": 40, "forYou": false, "reason": "vague oracle listing, little to grab" },
  { "id": "7d6feae4-459e-4614-ad3a-1d2e5d2dce27", "score": 68, "forYou": true, "reason": "authentic relating, meet people meaningfully" },
  { "id": "2d3d4cb3-a85d-4b88-8698-9e51b0ca3dde", "score": 58, "forYou": false, "reason": "inner-demon ritual with drums, curious but woo" },
  { "id": "39b436a0-baf6-4112-ad8c-1968e6b9adcd", "score": 30, "forYou": false, "reason": "joke listing, nothing to attend" },
  { "id": "39e6b9e1-3862-429b-b89a-482f0bcfbedb", "score": 50, "forYou": false, "reason": "playful philosophy chat, mildly interesting" },
  { "id": "70a5e269-3714-40f0-adbe-50beb76c073d", "score": 47, "forYou": false, "reason": "communal totem craft, sweet but insider" },
  { "id": "25dca9cb-6534-41ba-a4ba-b848d1e910f4", "score": 46, "forYou": false, "reason": "vague drop-in mug gathering" },
  { "id": "bce0c369-df16-4f7c-a643-766acb83e619", "score": 38, "forYou": false, "reason": "cryptic rocket-throwing, low-effort listing" },
  { "id": "cb8e5d78-f5e3-4021-9b8d-c017c93a2700", "score": 64, "forYou": false, "reason": "make leather nipple pasties, playful craft" },
  { "id": "98345c24-98fd-430b-81bc-a9f6b7966273", "score": 62, "forYou": false, "reason": "playful scream-and-growl vocal class" },
  { "id": "ffff73b2-9045-43ea-bb2f-4f06e07eb9c6", "score": 84, "forYou": true, "reason": "Arab disco and watermelon slushies, dancefloor gold" },
  { "id": "524aefe2-5d12-41eb-abd4-bebaf75fe3d3", "score": 66, "forYou": true, "reason": "taste-bending flavor tasting, playful and social" },
  { "id": "ec26e0e8-5dc8-4c7d-a252-6302ea113006", "score": 68, "forYou": true, "reason": "drum circle, dance and connect wordlessly" },
  { "id": "be381bb8-0296-4db4-a866-836a0420b3bd", "score": 58, "forYou": false, "reason": "deception performance game, fun social play" },
  { "id": "7920a868-d072-492b-8c8c-0c4d63618886", "score": 22, "forYou": false, "reason": "men-only erotic wrestling, no couple angle" },
  { "id": "a2cb5f1c-f1bc-4eae-a7ff-2eb0d06924be", "score": 52, "forYou": false, "reason": "life drawing session, low-detail listing" },
  { "id": "43263c5f-112a-41b4-b7cc-7f7e99ac8784", "score": 60, "forYou": false, "reason": "kundalini energy activation, deep surrender experience" },
  { "id": "ef01c8ad-3266-4800-8666-1f70352ee025", "score": 76, "forYou": true, "reason": "contemporary dance meets club, movement play" },
  { "id": "59f57eba-9a46-4207-b46f-7f10127494d4", "score": 74, "forYou": true, "reason": "naked dancefloor with indoor rain, inclusive" },
  { "id": "019140ec-e1fe-424f-a2db-b3b1e75935a6", "score": 70, "forYou": true, "reason": "36-questions intimacy game with a twist" },
  { "id": "da8b6020-575a-4fbe-8d73-5b1cac697a3b", "score": 68, "forYou": true, "reason": "daytime playspace, bring a buddy" },
  { "id": "a82f1104-19d5-460e-95b0-2eec88e3b2ae", "score": 72, "forYou": true, "reason": "beginner-friendly BDSM intro, playful and light" },
  { "id": "968b2380-6bbd-4dc0-b4b6-81c424d6deae", "score": 46, "forYou": false, "reason": "vague trash cabaret, could be fun" },
  { "id": "2b781952-dcfa-45a4-b84d-91f8281d2702", "score": 71, "forYou": true, "reason": "ecstatic dance to classical, delightfully unusual" },
  { "id": "7925286e-8238-463d-821a-f4792fdd8b0b", "score": 68, "forYou": true, "reason": "absurd formal-up-top cava aperitif, silly fun" },
  { "id": "b555cebe-1dea-4b73-83b7-76fdda53222c", "score": 66, "forYou": true, "reason": "naked karaoke, celebratory and inclusive singing" },
  { "id": "181cd86c-125b-425b-9a2a-52e4cef2d23e", "score": 65, "forYou": true, "reason": "charming French café with champagne, social" },
  { "id": "78cccce7-efc1-4935-9aa1-daa756ba5d5c", "score": 40, "forYou": false, "reason": "chess variants, niche unless you play" },
  { "id": "1fb49dd1-2432-44e3-ad8a-dd10fd97e5c1", "score": 62, "forYou": false, "reason": "Kiwi tasting menu, small food treat" },
  { "id": "0524c4a2-d2bb-4103-b341-488e0f681b79", "score": 66, "forYou": true, "reason": "make allioli, taste and kiss playfully" },
  { "id": "9198f442-e40f-45b3-b071-6c46810d4769", "score": 62, "forYou": false, "reason": "shoegaze and post-rock listening, mellow vibes" },
  { "id": "bb7f4570-cf68-4a7e-8b9f-0d7bc62dc014", "score": 20, "forYou": false, "reason": "BIPOC-only craft space, not for you" },
  { "id": "e90e65a9-68e0-44b3-8c7d-bd1df03cb2a9", "score": 64, "forYou": false, "reason": "heart-opening guided meditation, gentle reset" },
  { "id": "149f1946-e5cc-45f2-8dde-3792d6ccee62", "score": 72, "forYou": true, "reason": "whimsical Egyptian tea party with DJs" },
  { "id": "58b6d345-fbc5-4ece-ab68-32446a10f63a", "score": 74, "forYou": true, "reason": "beginner acroyoga, come with your partner" },
  { "id": "46c696a6-5c06-4f0a-b758-a6ff4692be0b", "score": 52, "forYou": false, "reason": "pole dancing under the sun, playful" },
  { "id": "5e283f50-5d8a-4192-b37e-b4478460bcc8", "score": 60, "forYou": false, "reason": "build a swamp cooler, nerdy team challenge" },
  { "id": "61ab425a-8450-4137-96a5-597bfd58045d", "score": 70, "forYou": true, "reason": "collective oil bath, tantric held ritual" },
  { "id": "1731f278-a50e-4ec8-ba2f-cac6d2759428", "score": 40, "forYou": false, "reason": "bare pole listing, minimal detail" },
  { "id": "b46c6249-a032-4810-8c4a-6546b8c87c01", "score": 48, "forYou": false, "reason": "French singalong, fun if francophone" },
  { "id": "496142d4-83d9-4ad2-b84f-b92c5c265d3d", "score": 54, "forYou": false, "reason": "paper airplane contest, silly light play" },
  { "id": "01f367e4-bf35-4886-a851-19a0d2d06042", "score": 58, "forYou": false, "reason": "goofy Pikachu playfight, absurd fun" },
  { "id": "a83aa248-9511-4fae-b287-cc0c253a8233", "score": 68, "forYou": true, "reason": "queer flamenco movement, expressive and welcoming" },
  { "id": "4f0841f2-d12f-4b4f-a90b-ea2eca69193a", "score": 60, "forYou": false, "reason": "naked play fighting, feral and playful" },
  { "id": "f3b7e801-2882-43b2-bc03-adb9f517c650", "score": 80, "forYou": true, "reason": "deep dub reggae soundsystem, bass heaven" },
  { "id": "5a54ca19-cf5d-404f-bfba-6a48a86d3e60", "score": 46, "forYou": false, "reason": "Top Gun volleyball, sporty themed fun" },
  { "id": "ef7ac6ee-94cb-4a1d-8670-a9dd64074c9c", "score": 62, "forYou": false, "reason": "rhythmic spanking to symphony, cheeky kink" },
  { "id": "e00d8ad3-39f4-4221-8d43-d593804cfebf", "score": 82, "forYou": true, "reason": "four-hour sunset funk DJ set, dance" },
  { "id": "17d0356f-df28-466b-9df9-e50da9da54f7", "score": 48, "forYou": false, "reason": "meteor juggling skill, niche prop play" },
  { "id": "ea0b5576-7c08-4ada-aa43-ccab07a8cb36", "score": 52, "forYou": false, "reason": "utopia talk, thoughtful but heavy" },
  { "id": "17e9b327-20eb-4cef-a8b7-6cbfe53284e6", "score": 55, "forYou": false, "reason": "dirty-talk language fetish, playful but niche" },
  { "id": "df157967-64a4-49f4-bdae-1485f8b6577b", "score": 70, "forYou": true, "reason": "body-positive naked party, dance and connect" },
  { "id": "9f0f4513-28f1-48ab-a030-bad551acbaa1", "score": 44, "forYou": false, "reason": "French-only improv RPG, language barrier" },
  { "id": "8ec462a1-e25b-4133-a9ea-8228a7287ae3", "score": 30, "forYou": false, "reason": "cock-and-ball torture, hyper-niche fetish" },
  { "id": "0a516c72-70ff-4d26-af9c-74d1ed75bffa", "score": 76, "forYou": true, "reason": "partnered blues dancing, connection and music" }
]
